{
  "status": "success",
  "data": {
    "top_losers": [
      {
        "ticker": "IBM",
        "change": "-24.88%"
      },
      {
        "ticker": "MRK",
        "change": "-2.88%"
      },
      {
        "ticker": "LLY",
        "change": "-2.46%"
      },
      {
        "ticker": "WFC",
        "change": "-2.26%"
      },
      {
        "ticker": "CMCSA",
        "change": "-1.77%"
      },
      {
        "ticker": "CSCO",
        "change": "-1.50%"
      },
      {
        "ticker": "JNJ",
        "change": "-1.94%"
      },
      {
        "ticker": "AAPL",
        "change": "-1.13%"
      },
      {
        "ticker": "MSFT",
        "change": "-1.01%"
      },
      {
        "ticker": "UNH",
        "change": "-0.87%"
      }
    ],
    "generated_at": "2026-07-14T16:43:14.472169Z",
    "source": "finviz"
  },
  "version": "1.0",
  "last_updated": "2026-07-14T16:43:14.472169Z"
}