{
  "status": "success",
  "data": {
    "top_losers": [
      {
        "ticker": "INTC",
        "change": "-3.41%"
      },
      {
        "ticker": "MPWR",
        "change": "-2.03%"
      },
      {
        "ticker": "LRCX",
        "change": "-2.63%"
      },
      {
        "ticker": "KO",
        "change": "-2.23%"
      },
      {
        "ticker": "GOOG",
        "change": "-1.61%"
      },
      {
        "ticker": "KLAC",
        "change": "-1.64%"
      },
      {
        "ticker": "CAT",
        "change": "-1.72%"
      },
      {
        "ticker": "MU",
        "change": "-1.92%"
      },
      {
        "ticker": "RTX",
        "change": "-1.41%"
      },
      {
        "ticker": "MRK",
        "change": "-1.21%"
      }
    ],
    "generated_at": "2026-02-10T15:52:21.929862Z",
    "source": "finviz"
  },
  "version": "1.0",
  "last_updated": "2026-02-10T15:52:21.929862Z"
}